atooms/__init__.py
atooms/voronoi/__init__.py
atooms/voronoi/_version.py
atooms/voronoi/api.py
atooms/voronoi/core.py
atooms/voronoi/helpers.py
atooms/voronoi/voronoi.py
atooms_voronoi-0.9.8.data/scripts/voro.py
atooms_voronoi-0.9.8.data/scripts/voropp.py
atooms_voronoi-0.9.8.dist-info/LICENSE
atooms_voronoi-0.9.8.dist-info/METADATA
atooms_voronoi-0.9.8.dist-info/WHEEL
atooms_voronoi-0.9.8.dist-info/top_level.txt
atooms_voronoi-0.9.8.dist-info/RECORD
