Metadata-Version: 2.1
Name: atooms-voronoi
Version: 0.9.8
Summary: Voronoi wrapper to voro++ and analysis tools
Home-page: https://framagit.org/atooms/voronoi
Author: Daniele Coslovich
Author-email: dcoslovich@umontpellier.fr
License: GPLv3
Classifier: License :: OSI Approved :: GNU General Public License v3 (GPLv3)
Classifier: Programming Language :: Python
License-File: LICENSE
Requires-Dist: atooms (>=3.0)
